aldryn_bootstrap3/__init__.py
aldryn_bootstrap3/cms_plugins.py
aldryn_bootstrap3/conf.py
aldryn_bootstrap3/constants.py
aldryn_bootstrap3/fields.py
aldryn_bootstrap3/forms.py
aldryn_bootstrap3/model_fields.py
aldryn_bootstrap3/models.py
aldryn_bootstrap3/widgets.py
aldryn_bootstrap3/locale/de/LC_MESSAGES/django.mo
aldryn_bootstrap3/locale/de/LC_MESSAGES/django.po
aldryn_bootstrap3/locale/en/LC_MESSAGES/django.mo
aldryn_bootstrap3/locale/en/LC_MESSAGES/django.po
aldryn_bootstrap3/locale/es/LC_MESSAGES/django.mo
aldryn_bootstrap3/locale/es/LC_MESSAGES/django.po
aldryn_bootstrap3/locale/fr/LC_MESSAGES/django.mo
aldryn_bootstrap3/locale/fr/LC_MESSAGES/django.po
aldryn_bootstrap3/locale/it/LC_MESSAGES/django.mo
aldryn_bootstrap3/locale/it/LC_MESSAGES/django.po
aldryn_bootstrap3/locale/ru/LC_MESSAGES/django.mo
aldryn_bootstrap3/locale/ru/LC_MESSAGES/django.po
aldryn_bootstrap3/migrations/0001_initial.py
aldryn_bootstrap3/migrations/0002_bootstrap3fileplugin.py
aldryn_bootstrap3/migrations/0003_auto_20151113_1604.py
aldryn_bootstrap3/migrations/0004_auto_20151211_1333.py
aldryn_bootstrap3/migrations/0005_boostrap3imageplugin_use_original_image.py
aldryn_bootstrap3/migrations/0006_auto_20160615_1740.py
aldryn_bootstrap3/migrations/0007_auto_20160705_1155.py
aldryn_bootstrap3/migrations/0008_auto_20160820_2332.py
aldryn_bootstrap3/migrations/0009_auto_20161219_1530.py
aldryn_bootstrap3/migrations/0010_bootstrap3codeplugin.py
aldryn_bootstrap3/migrations/0011_bootstrap3responsiveplugin.py
aldryn_bootstrap3/migrations/0012_bootstrap3tabplugin.py
aldryn_bootstrap3/migrations/0013_boostrap3jumbotronplugin.py
aldryn_bootstrap3/migrations/0014_translations_update.py
aldryn_bootstrap3/migrations/__init__.py
aldryn_bootstrap3/static/aldryn_bootstrap3/css/base.css
aldryn_bootstrap3/static/aldryn_bootstrap3/css/bootstrap-iconpicker.min.css
aldryn_bootstrap3/static/aldryn_bootstrap3/css/bootstrap.min.css
aldryn_bootstrap3-1.3.0.dist-info/DESCRIPTION.rst
aldryn_bootstrap3-1.3.0.dist-info/METADATA
aldryn_bootstrap3-1.3.0.dist-info/RECORD
aldryn_bootstrap3-1.3.0.dist-info/WHEEL
aldryn_bootstrap3-1.3.0.dist-info/metadata.json
aldryn_bootstrap3-1.3.0.dist-info/top_level.txt
