Metadata-Version: 2.0
Name: aldryn-bootstrap3
Version: 1.3.0
Summary: Adds Bootstrap 3 components as plugins.
Home-page: https://github.com/aldryn/aldryn-bootstrap3
Author: Divio AG
Author-email: info@divio.ch
License: BSD
Platform: UNKNOWN
Classifier: Development Status :: 5 - Production/Stable
Classifier: Environment :: Web Environment
Classifier: Framework :: Django
Classifier: Intended Audience :: Developers
Classifier: License :: OSI Approved :: BSD License
Classifier: Operating System :: OS Independent
Classifier: Programming Language :: Python
Classifier: Programming Language :: Python :: 2
Classifier: Programming Language :: Python :: 2.7
Classifier: Programming Language :: Python :: 3
Classifier: Programming Language :: Python :: 3.4
Classifier: Programming Language :: Python :: 3.5
Classifier: Topic :: Internet :: WWW/HTTP
Classifier: Topic :: Internet :: WWW/HTTP :: Dynamic Content
Classifier: Topic :: Software Development :: Libraries :: Application Frameworks
Classifier: Topic :: Software Development :: Libraries :: Python Modules
Requires-Dist: django-appconf (>=1.0.0)
Requires-Dist: django-cms (>=3.3.0)
Requires-Dist: django-filer (>=0.9.11)
Requires-Dist: djangocms-attributes-field (>=0.1.1)
Requires-Dist: djangocms-text-ckeditor (>=3.1.0)
